{"inkVersion":21,"root":[["\n","ev",{"VAR?":"foodOrdered"},"/ev",[{"->":".^.b","c":true},{"b":["\n",["ev","visit",4,"seq","/ev","ev","du",0,"==","/ev",{"->":".^.s0","c":true},"ev","du",1,"==","/ev",{"->":".^.s1","c":true},"ev","du",2,"==","/ev",{"->":".^.s2","c":true},"ev","du",3,"==","/ev",{"->":".^.s3","c":true},"nop",{"s0":["pop","^Mama：Hold on, the stuff will be ready soon.",{"->":".^.^.29"},null],"s1":["pop","^Mama：Just a minute.",{"->":".^.^.29"},null],"s2":["pop","^Mama：Make yourself comfortable while you wait.",{"->":".^.^.29"},null],"s3":["pop","^Mama：On it!",{"->":".^.^.29"},null],"#f":5}],"#","^profile: mama_norm","/#","\n","done",{"->":"0.5"},null]}],"nop","\n","ev",{"VAR?":"mamaTalk"},"/ev",["du","ev",0,"==","/ev",{"->":".^.b","c":true},{"b":["pop","\n","ev",{"VAR?":"mamaTalk"},1,"+",{"VAR=":"mamaTalk","re":true},"/ev",{"->":"first_talk"},{"->":"0.12"},null]}],[{"->":".^.b"},{"b":["pop","\n","ev",{"VAR?":"mamaTalk"},1,"+",{"VAR=":"mamaTalk","re":true},"/ev",{"->":"talk_again"},{"->":"0.12"},null]}],"nop","\n",["done",{"#f":5,"#n":"g-0"}],null],"done",{"first_talk":[["^Mama：Hey, it's the painter! You'll have the usual?","#","^profile: mama_satisfied","/#","\n","^Me：(What should I order?)","#","^profile：painter_happy","/#","\n","ev","str","^Spare Ribs Casserole(￥12)","/str","/ev",{"*":".^.c-0","flg":4},"ev","str","^BBQ set(￥16)","/str","/ev",{"*":".^.c-1","flg":4},"ev","str","^I'm out of cash","/str","/ev",{"*":".^.c-2","flg":4},{"c-0":["\n","ev",{"VAR?":"money"},12,"<","/ev",[{"->":".^.b","c":true},{"b":["\n","^Me：(The casserole here is a real treat, even better with some bean sprouts...wait, I think I forgot something.）","#","^profile：painter_eyeClosed","/#","\n",{"->":"no_money"},{"->":".^.^.^.8"},null]}],[{"->":".^.b"},{"b":["\n","^Me：I'll have the Spare Ribs Casserole with rice!","#","^addMoney: -12 ","/#","#","^profile：painter_happy","/#","\n",{"->":"you_know_displace"},{"->":".^.^.^.8"},null]}],"nop","\n",{"#f":5}],"c-1":["\n","ev",{"VAR?":"money"},16,"<","/ev",[{"->":".^.b","c":true},{"b":["\n","^Me：(The BBQ set looks good, but...)","#","^profile：painter_eyeClosed","/#","\n",{"->":"no_money"},{"->":".^.^.^.8"},null]}],[{"->":".^.b"},{"b":["\n","^Me：I'll have the BBQ set! Lamb kebabs and grilled eggplant, please.","#","^addMoney: -16 ","/#","#","^profile：painter_happy","/#","\n",{"->":"you_know_displace"},{"->":".^.^.^.8"},null]}],"nop","\n",{"#f":5}],"c-2":["\n",{"->":"no_money"},{"#f":5}]}],{"#f":1}],"you_know_displace":[["^Mama：Coming right up!","#","^profile: mama_satisfied","/#","\n","^Mama：You didn't hesitate to pay, I'll take it that you already know about displacement?","#","^profile: mama_norm","/#","\n","ev","str","^Of Course","/str","/ev",{"*":".^.c-0","flg":4},"ev","str","^Displacement?","/str","/ev",{"*":".^.c-1","flg":4},{"c-0":["\n","^Me：Of Course.","\n","^Mama：Ha, I understand.","\n",{"->":"buy_food"},{"#f":5}],"c-1":["\n",{"->":"explain_displace"},{"#f":5}]}],{"#f":1}],"talk_again":[["^Mama：What would you like to have?","#","^profile: mama_norm","/#","\n","ev","str","^Spare Ribs Casserole(￥12)","/str",{"VAR?":"money"},12,">","/ev",{"*":".^.c-0","flg":5},"ev","str","^BBQ Set(￥16)","/str",{"VAR?":"money"},16,">","/ev",{"*":".^.c-1","flg":5},"ev","str","^Uhhhh.","/str","/ev",{"*":".^.c-2","flg":4},{"c-0":["\n","^Me：I'll have the Spare Ribs Casserole with rice!","#","^addMoney: -12 ","/#","#","^profile：painter_happy","/#","\n",{"->":"buy_food"},{"#f":5}],"c-1":["\n","^Me：I'll have the BBQ set! Lamb kebabs and grilled eggplant, please.","#","^addMoney: -16 ","/#","#","^profile：painter_happy","/#","\n",{"->":"buy_food"},{"#f":5}],"c-2":["\n","^Mama：Just displace something.","#","^profile: mama_upset","/#","\n","done",{"#f":5}]}],{"#f":1}],"no_money":["^Me：......... ","#","^profile：painter_side","/#","\n","^Me：...I'm out of cash...Could you please kindheartedly give me some plain noodles, I'm so sorry...I'll sell a painting tomorrow and pay it back.","#","^profile: painter_sideSweat","/#","\n","^Mama：How come you're broke?","#","^profile: mama_norm","/#","\n","^Me：To be honest, I'm not sure. I woke up and everything's gone.","#","^profile: painter_depressed","/#","\n","^Me：(Crap, I sound like a shameless lier.）","#","^profile: painter_sideSweat","/#","\n","^Mama：Right. You're a regular here, it's not like I don't trust you. It's okay to cook you something to eat.","#","^profile: mama_upset","/#","\n","^Mama：But you're carrying quite a few things with you.","#","^profile: mama_upset","/#","\n","^Mama：Why don't you <color=magenta>displace</color> something for cash?","#","^profile: mama_norm","/#","\n","^Me：Displacement.","#","^profile: painter_sour","/#","\n","^Me：(Right, displacement...)","#","^profile: painter_eyeClosed ","/#","#","^unlockNote: 2_3","/#","\n",{"->":"explain_displace"},{"#f":1}],"explain_displace":["^Mama：What's wrong? You still can't figure out displacement? Why, you're not like a young person. Everyone displaces here.","#","^profile: mama_upset","/#","\n","^Mama：Just focus on the thought of turning this thing into money--see, how hard is that?","#","^profile: mama_satisfied","/#","\n","ev",{"CNT?":"you_know_displace"},"!","/ev",[{"->":".^.b","c":true},{"b":["\n","^Mama：Your turn. Displace something, and I promise I'll make you a delicious meal.","\n","^Me：(The rule of thumb of displacement: the more important something is to me, the more it's worth in cash.)","#","^profile: painter_norm","/#","\n","^Me：(Of course, the status of an object in one's mind changes, and so does its worth. Most people can't accurately predict how much something is worth. That's a risk you'll have to take.）","\n","^Me：(Displacement has become a magic that everyone can do, whenever and wherever they want.）","\n","^Me：(However, as a means of quick money, displacement has a <color=magenta>price</color> that I just hate to afford: <color=gray>disappearance</color>.）","\n",{"->":".^.^.^.15"},null]}],"nop","\n","ev",{"CNT?":"you_know_displace"},"/ev",[{"->":".^.b","c":true},{"b":["\n","^Me：(What's wrong with me! I don't even remember the whole displacement thing.）","\n","^Mama：Painter, what's on your mind?","#","^profile: mama_norm","/#","\n","^Me：(Lost in my thoughts again.）Nothing! Sorry.","#","^profile：painter_side","/#","\n","^Mama：Haha, you're like a child.","#","^profile:mama_satisfied","/#","\n",{"->":"buy_food"},{"->":".^.^.^.21"},null]}],"nop","\n","^Me：.........","#","^profile：painter_eyeClosed ","/#","#","^unlockNote: 2_4","/#","\n","^Me：(I really can't pull myself together to beg for food, so I'd better see if there's anything worth displacing.)","#","^event: showDisplace","/#","\n","done",{"#f":1}],"buy_food":["ev",true,"/ev",{"VAR=":"foodOrdered","re":true},"^Mama：Sit down and wait! The food will be ready in three minutes.","#","^profile: mama_satisfied ","/#","#","^event: mama_back","/#","\n","done",{"#f":1}],"finish_displace":["^Me：(That's it? Well, I have some money now.)","\n","^Me：(Wait, what did I just trade away?)","\n","^Me：(Such a pain in the ass. Stop trying to remember it--it just disappeared, leaving no trace of existence.）","#","^unlockNote: 3_1","/#","\n","^Me：(Anyways, it doesn't matter. Now I can buy something from Mama.)","\n","done","end",{"#f":1}],"global decl":["ev",0,{"VAR=":"money"},0,{"VAR=":"mamaTalk"},false,{"VAR=":"foodOrdered"},0,{"VAR=":"anaTalk"},0,{"VAR=":"lwTalk"},"str","^永不售空","/str",{"VAR=":"lwText_CH"},"str","^Nothing's ever sold out","/str",{"VAR=":"lwText_EN"},0,{"VAR=":"iceEatTalk"},false,{"VAR=":"diyRead"},"str","^","/str",{"VAR=":"findPerson_CH"},"str","^","/str",{"VAR=":"findPerson_EN"},"/ev","end",null],"#f":1}],"listDefs":{}}